shiftES/__init__.py
shiftES/shift_effectsize.py
shiftES/shiftes.py
shiftES/tests.py
shiftES-1.0.7.data/scripts/shift_effectsize.py
shiftES-1.0.7.dist-info/LICENSE
shiftES-1.0.7.dist-info/METADATA
shiftES-1.0.7.dist-info/WHEEL
shiftES-1.0.7.dist-info/top_level.txt
shiftES-1.0.7.dist-info/RECORD
